arize/__init__.py
arize/api.py
arize/bounded_executor.py
arize/public_pb2.py
arize/version.py
arize/experimental/__init__.py
arize/experimental/datasets/__init__.py
arize/experimental/datasets/core/__init__.py
arize/experimental/datasets/core/client.py
arize/experimental/datasets/core/session.py
arize/experimental/datasets/experiments/__init__.py
arize/experimental/datasets/experiments/functions.py
arize/experimental/datasets/experiments/tracing.py
arize/experimental/datasets/experiments/types.py
arize/experimental/datasets/experiments/evaluators/__init__.py
arize/experimental/datasets/experiments/evaluators/base.py
arize/experimental/datasets/experiments/evaluators/exceptions.py
arize/experimental/datasets/experiments/evaluators/executors.py
arize/experimental/datasets/experiments/evaluators/rate_limiters.py
arize/experimental/datasets/experiments/evaluators/utils.py
arize/experimental/datasets/utils/__init__.py
arize/experimental/datasets/utils/constants.py
arize/experimental/datasets/utils/experiment_utils.py
arize/experimental/datasets/validation/__init__.py
arize/experimental/datasets/validation/errors.py
arize/experimental/datasets/validation/validator.py
arize/experimental/integrations/whylabs/__init__.py
arize/experimental/integrations/whylabs/client.py
arize/experimental/integrations/whylabs/generator.py
arize/experimental/integrations/whylabs/test.py
arize/experimental/integrations/whylabs_vanguard_governance/__init__.py
arize/experimental/integrations/whylabs_vanguard_governance/client.py
arize/experimental/integrations/whylabs_vanguard_governance/test.py
arize/experimental/integrations/whylabs_vanguard_ingestion/__init__.py
arize/experimental/integrations/whylabs_vanguard_ingestion/client.py
arize/experimental/integrations/whylabs_vanguard_ingestion/generator.py
arize/experimental/integrations/whylabs_vanguard_ingestion/test.py
arize/experimental/online_tasks/__init__.py
arize/experimental/online_tasks/dataframe_preprocessor.py
arize-7.51.2.dist-info/METADATA
arize-7.51.2.dist-info/WHEEL
arize-7.51.2.dist-info/licenses/LICENSE.md
arize-7.51.2.dist-info/RECORD
