Metadata-Version: 2.4
Name: arize
Version: 7.51.2
Summary: A helper library to interact with Arize AI APIs
Project-URL: Homepage, https://arize.com
Project-URL: Documentation, https://docs.arize.com/arize
Project-URL: Issues, https://github.com/Arize-ai/client_python/issues
Project-URL: Source, https://github.com/Arize-ai/client_python
Project-URL: Changelog, https://github.com/Arize-ai/client_python/blob/main/CHANGELOG.md
Author-email: Arize AI <support@arize.com>
Maintainer-email: Arize AI <support@arize.com>
License: BSD
License-File: LICENSE.md
Keywords: Arize,Evaluations,Explainability,LLM,Monitoring,Observability,Tracing
Classifier: Development Status :: 5 - Production/Stable
Classifier: Intended Audience :: Developers
Classifier: Programming Language :: Python
Classifier: Programming Language :: Python :: 3.6
Classifier: Programming Language :: Python :: 3.7
Classifier: Programming Language :: Python :: 3.8
Classifier: Programming Language :: Python :: 3.9
Classifier: Programming Language :: Python :: 3.10
Classifier: Programming Language :: Python :: 3.11
Classifier: Programming Language :: Python :: 3.12
Classifier: Programming Language :: Python :: 3.13
Classifier: Topic :: Scientific/Engineering :: Artificial Intelligence
Classifier: Topic :: Software Development :: Libraries :: Python Modules
Classifier: Topic :: System :: Logging
Classifier: Topic :: System :: Monitoring
Requires-Python: >=3.6
Requires-Dist: googleapis-common-protos<2,>=1.51.0
Requires-Dist: pandas<3,>=0.25.3
Requires-Dist: protobuf<7,>=4.21.0
Requires-Dist: pyarrow>=0.15.0
Requires-Dist: pydantic<3,>=2.0.0
Requires-Dist: requests-futures==1.0.0
Requires-Dist: tqdm<5,>=4.60.0
Provides-Extra: autoembeddings
Requires-Dist: datasets!=2.14.*,<3,>=2.8; extra == 'autoembeddings'
Requires-Dist: pillow<11,>=8.4.0; extra == 'autoembeddings'
Requires-Dist: tokenizers<1,>=0.13; extra == 'autoembeddings'
Requires-Dist: torch<3,>=1.13; extra == 'autoembeddings'
Requires-Dist: transformers<5,>=4.25; extra == 'autoembeddings'
Provides-Extra: datasets
Requires-Dist: deprecated; extra == 'datasets'
Requires-Dist: openinference-semantic-conventions<1,>=0.1.6; extra == 'datasets'
Requires-Dist: opentelemetry-exporter-otlp<2,>=1.25.0; extra == 'datasets'
Requires-Dist: opentelemetry-sdk<2,>=1.25.0; extra == 'datasets'
Requires-Dist: opentelemetry-semantic-conventions<1,>=0.43b0; extra == 'datasets'
Requires-Dist: typing-extensions<5,>=4; extra == 'datasets'
Requires-Dist: wrapt<2,>=1.12.1; extra == 'datasets'
Provides-Extra: dev
Requires-Dist: pytest==8.3.3; extra == 'dev'
Requires-Dist: ruff==0.6.9; extra == 'dev'
Provides-Extra: llm-evaluation
Requires-Dist: datasets!=2.14.*; extra == 'llm-evaluation'
Requires-Dist: evaluate<1,>=0.3; extra == 'llm-evaluation'
Requires-Dist: nltk<4,>=3.0.0; extra == 'llm-evaluation'
Requires-Dist: rouge-score<1,>=0.1.2; extra == 'llm-evaluation'
Requires-Dist: sacrebleu<3,>=2.3.1; extra == 'llm-evaluation'
Provides-Extra: mimicexplainer
Requires-Dist: interpret-community[mimic]<1,>=0.22.0; extra == 'mimicexplainer'
Provides-Extra: nlp-metrics
Requires-Dist: datasets!=2.14.*; extra == 'nlp-metrics'
Requires-Dist: evaluate<1,>=0.3; extra == 'nlp-metrics'
Requires-Dist: nltk<4,>=3.0.0; extra == 'nlp-metrics'
Requires-Dist: rouge-score<1,>=0.1.2; extra == 'nlp-metrics'
Requires-Dist: sacrebleu<3,>=2.3.1; extra == 'nlp-metrics'
Provides-Extra: prompthub
Requires-Dist: gql<4.0.0,>=3.0.0; extra == 'prompthub'
Requires-Dist: requests-toolbelt>=1.0.0; extra == 'prompthub'
Provides-Extra: prompthub-vertexai
Requires-Dist: google-cloud-aiplatform>=1.0.0; extra == 'prompthub-vertexai'
Provides-Extra: tracing
Requires-Dist: deprecated; extra == 'tracing'
Requires-Dist: openinference-semantic-conventions<1,>=0.1.12; extra == 'tracing'
Requires-Dist: opentelemetry-semantic-conventions<1,>=0.43b0; extra == 'tracing'
